{"MSM": [{"Enrollment no:": "17312003", "Name:": "AKSHIT MITTAL", "Company:": "Goldman Sachs Services Private Ltd.", "Course:": "IMSc", "Accepted:": "Yes "}, {"Enrollment no:": "17312004", "Name:": "AMAN DUBEY", "Company:": "Microsoft India Pvt. Ltd. (SE)", "Course:": "IMSc", "Accepted:": "Yes "}, {"Enrollment no:": "17312011", "Name:": "HARSH KUMAR CHOURASIA", "Company:": "Sprinklr(Product Engineer)", "Course:": "IMSc", "Accepted:": "Yes "}, {"Enrollment no:": "17312019", "Name:": "PARTH KOHLI", "Company:": "Sprinklr(Product Engineer)", "Course:": "IMSc", "Accepted:": "Yes "}, {"Enrollment no:": "17312019", "Name:": "PARTH KOHLI", "Company:": "D. E. Shaw India", "Course:": "IMSc", "Accepted:": "No"}, {"Enrollment no:": "17312019", "Name:": "PARTH KOHLI", "Company:": "Uber", "Course:": "IMSc", "Accepted:": "No"}, {"Enrollment no:": "17312024", "Name:": "SAVISH BEDI", "Company:": "Microsoft (PIO)", "Course:": "IMSc", "Accepted:": "Yes "}], "CH": [{"Enrollment no:": "18118018", "Name:": "AYUSH SINGH", "Company:": "Goldman Sachs Services Private Ltd.", "Course:": "B.Tech.", "Accepted:": "Yes "}, {"Enrollment no:": "18118083", "Name:": "VINAY RAJENDRA AGARWAL", "Company:": "Goldman Sachs Services Private Ltd.", "Course:": "B.Tech.", "Accepted:": "Yes "}], "CE": [{"Enrollment no:": "18113011", "Name:": "ANADI VYAS", "Company:": "Nutanix", "Course:": "B.Tech.", "Accepted:": "Yes "}, {"Enrollment no:": "18113031", "Name:": "ASTHA JYOTI", "Company:": "Microsoft India Pvt. Ltd. (SE)", "Course:": "B.Tech.", "Accepted:": "Yes "}, {"Enrollment no:": "18113082", "Name:": "MEGHUL TYAGI", "Company:": "American Express (Analytics)", "Course:": "B.Tech.", "Accepted:": "Yes "}], "CSE": [{"Enrollment no:": "18114003", "Name:": "ABHISHEK PATIL", "Company:": "Sprinklr(Product Engineer)", "Course:": "B.Tech.", "Accepted:": "Yes "}, {"Enrollment no:": "18114016", "Name:": "AYUSH MANGAL", "Company:": "Microsoft India Pvt. Ltd. (ML)", "Course:": "B.Tech.", "Accepted:": "Yes "}, {"Enrollment no:": "18114017", "Name:": "BALNE NITEESHA", "Company:": "Microsoft India Pvt. Ltd. (SE)", "Course:": "B.Tech.", "Accepted:": "Yes "}, {"Enrollment no:": "18119010", "Name:": "DEVJIT MENGHANI", "Company:": "Microsoft India Pvt. Ltd. (SE)", "Course:": "B.Tech.", "Accepted:": "Yes "}, {"Enrollment no:": "18119010", "Name:": "DEVJIT MENGHANI", "Company:": "Quadeye", "Course:": "B.Tech.", "Accepted:": "No"}, {"Enrollment no:": "18114019", "Name:": "DIKSHA", "Company:": "AppDynamics Technologies India Private  Limited", "Course:": "B.Tech.", "Accepted:": "Yes "}, {"Enrollment no:": "18115037", "Name:": "GURDEEP SINGH OBEROI", "Company:": "Quadeye", "Course:": "B.Tech.", "Accepted:": "Yes "}, {"Enrollment no:": "18114029", "Name:": "HARSHIT VERMA", "Company:": "D. E. Shaw India", "Course:": "B.Tech.", "Accepted:": "Yes "}, {"Enrollment no:": "18114031", "Name:": "HEMIL SANJAYBHAI PANCHIWALA", "Company:": "American Express (Technology)", "Course:": "B.Tech.", "Accepted:": "Yes "}, {"Enrollment no:": "18113061", "Name:": "ISHAN PANDEY", "Company:": "Goldman Sachs Services Private Ltd.", "Course:": "B.Tech.", "Accepted:": "Yes "}, {"Enrollment no:": "18114036", "Name:": "KARANPREET SINGH", "Company:": "Microsoft India Pvt. Ltd. (SE)", "Course:": "B.Tech.", "Accepted:": "No"}, {"Enrollment no:": "18114036", "Name:": "KARANPREET SINGH", "Company:": "Adobe (Direct Offer)", "Course:": "B.Tech.", "Accepted:": "Yes "}, {"Enrollment no:": "18114043", "Name:": "KURAPATI PRANEETH", "Company:": "Microsoft India Pvt. Ltd. (SE)", "Course:": "B.Tech.", "Accepted:": "Yes "}, {"Enrollment no:": "18114044", "Name:": "LESHNA BALARA", "Company:": "Google (PIO)", "Course:": "B.Tech.", "Accepted:": "Yes "}, {"Enrollment no:": "18114050", "Name:": "NAVEEN BANSAL", "Company:": "Nutanix", "Course:": "B.Tech.", "Accepted:": "Yes "}, {"Enrollment no:": "18114051", "Name:": "NIHARIKA AGRAWAL", "Company:": "Goldman Sachs Services Private Ltd.", "Course:": "B.Tech.", "Accepted:": "No"}, {"Enrollment no:": "18114051", "Name:": "NIHARIKA AGRAWAL", "Company:": "Google SWE", "Course:": "B.Tech.", "Accepted:": "Yes "}, {"Enrollment no:": "18114052", "Name:": "NISHANT JAIN", "Company:": "Microsoft India Pvt. Ltd. (ML)", "Course:": "B.Tech.", "Accepted:": "Yes "}, {"Enrollment no:": "18114054", "Name:": "PALASH GARG", "Company:": "Microsoft India Pvt. Ltd. (SE)", "Course:": "B.Tech.", "Accepted:": "Yes "}, {"Enrollment no:": "18114056", "Name:": "PRATEEK SACHAN", "Company:": "Microsoft India Pvt. Ltd. (SE)", "Course:": "B.Tech.", "Accepted:": "Yes "}, {"Enrollment no:": "18114057", "Name:": "PRIYANSH AGARWAL", "Company:": "Microsoft India Pvt. Ltd. (SE)", "Course:": "B.Tech.", "Accepted:": "Yes "}, {"Enrollment no:": "18114060", "Name:": "RADHIKA", "Company:": "Google (PIO)", "Course:": "B.Tech.", "Accepted:": "Yes "}, {"Enrollment no:": "18118052", "Name:": "RISHI CHORDIA", "Company:": "Microsoft India Pvt. Ltd. (SE)", "Course:": "B.Tech.", "Accepted:": "Yes "}, {"Enrollment no:": "18114069", "Name:": "RITIKA GARG", "Company:": "Microsoft India Pvt. Ltd. (SE)", "Course:": "B.Tech.", "Accepted:": "Yes "}, {"Enrollment no:": "18114070", "Name:": "RUTUJA BHAGWAN KENDRE", "Company:": "Microsoft India Pvt. Ltd. (SE)", "Course:": "B.Tech.", "Accepted:": "Yes "}, {"Enrollment no:": "18117106", "Name:": "SURAAJ K S", "Company:": "Google Hardware", "Course:": "B.Tech.", "Accepted:": "Yes "}, {"Enrollment no:": "18114079", "Name:": "UNMESH KUMAR", "Company:": "Google SWE", "Course:": "B.Tech.", "Accepted:": "Yes "}], "EE": [{"Enrollment no:": "18115022", "Name:": "ARYAN RAJ", "Company:": "American Express (Technology)", "Course:": "B.Tech.", "Accepted:": "Yes "}, {"Enrollment no:": "18117019", "Name:": "AYAN CHOUDHARY", "Company:": "Microsoft India Pvt. Ltd. (SE)", "Course:": "B.Tech.", "Accepted:": "Yes "}, {"Enrollment no:": "18115043", "Name:": "ISHITA SAINI", "Company:": "Goldman Sachs Services Private Ltd.", "Course:": "B.Tech.", "Accepted:": "Yes "}, {"Enrollment no:": "18121012", "Name:": "JAYATI SHRIVASTAVA", "Company:": "Google Hardware", "Course:": "B.Tech.", "Accepted:": "Yes "}, {"Enrollment no:": "18115051", "Name:": "KHUSHI", "Company:": "Adobe (Direct Offer)", "Course:": "B.Tech.", "Accepted:": "Yes "}, {"Enrollment no:": "18115058", "Name:": "MAYANK SINGHAL", "Company:": "Microsoft India Pvt. Ltd. (SE)", "Course:": "B.Tech.", "Accepted:": "Yes "}, {"Enrollment no:": "18115063", "Name:": "NAMRATA MEENA", "Company:": "Goldman Sachs Services Private Ltd.", "Course:": "B.Tech.", "Accepted:": "Yes "}, {"Enrollment no:": "18115065", "Name:": "NIHARIKA MATHUR", "Company:": "Microsoft India Pvt. Ltd. (SE)", "Course:": "B.Tech.", "Accepted:": "Yes "}, {"Enrollment no:": "18115074", "Name:": "RAHUL AHLAWAT", "Company:": "American Express (Technology)", "Course:": "B.Tech.", "Accepted:": "Yes "}, {"Enrollment no:": "18115077", "Name:": "RAHUL RAWAL", "Company:": "Nutanix", "Course:": "B.Tech.", "Accepted:": "Yes "}, {"Enrollment no:": "18121021", "Name:": "SARA SINGHAL", "Company:": "American Express (Technology)", "Course:": "B.Tech.", "Accepted:": "Yes "}, {"Enrollment no:": "18115096", "Name:": "SHIVANG BHAWSAR", "Company:": "Microsoft India Pvt. Ltd. (SE)", "Course:": "B.Tech.", "Accepted:": "No"}, {"Enrollment no:": "18115096", "Name:": "SHIVANG BHAWSAR", "Company:": "Goldman Sachs Services Private Ltd.", "Course:": "B.Tech.", "Accepted:": "Yes "}, {"Enrollment no:": "18115103", "Name:": "SHUBHANG PANDEY", "Company:": "Uber", "Course:": "B.Tech.", "Accepted:": "Yes "}, {"Enrollment no:": "18115106", "Name:": "SRASTI SETHI", "Company:": "Microsoft India Pvt. Ltd. (SE)", "Course:": "B.Tech.", "Accepted:": "Yes "}, {"Enrollment no:": "18115111", "Name:": "TANISHA SAHU", "Company:": "Goldman Sachs Services Private Ltd.", "Course:": "B.Tech.", "Accepted:": "Yes "}, {"Enrollment no:": "18115116", "Name:": "URJITA SHARMA", "Company:": "Google Hardware", "Course:": "B.Tech.", "Accepted:": "Yes "}, {"Enrollment no:": "18115116", "Name:": "URJITA SHARMA", "Company:": "JP Morgan (Quant)", "Course:": "B.Tech.", "Accepted:": "No"}, {"Enrollment no:": "18115120", "Name:": "VIKRANT GUPTA", "Company:": "ITC", "Course:": "B.Tech.", "Accepted:": "Yes "}], "ECE": [{"Enrollment no:": "18116003", "Name:": "ADITYA KUMAR SINGH", "Company:": "JP Morgan (Quant)", "Course:": "B.Tech.", "Accepted:": "Yes "}, {"Enrollment no:": "18116013", "Name:": "ANMOL AGARWAL", "Company:": "Google SWE", "Course:": "B.Tech.", "Accepted:": "Yes "}, {"Enrollment no:": "18116021", "Name:": "AYUSH SINGH", "Company:": "Goldman Sachs Services Private Ltd.", "Course:": "B.Tech.", "Accepted:": "No"}, {"Enrollment no:": "18116021", "Name:": "AYUSH SINGH", "Company:": "Microsoft India Pvt. Ltd. (SE)", "Course:": "B.Tech.", "Accepted:": "Yes "}, {"Enrollment no:": "18116030", "Name:": "HARSHIT GOENKA", "Company:": "AppDynamics Technologies India Private  Limited", "Course:": "B.Tech.", "Accepted:": "Yes "}, {"Enrollment no:": "18116032", "Name:": "ISHITA KAUL", "Company:": "Google (PIO)", "Course:": "B.Tech.", "Accepted:": "Yes "}, {"Enrollment no:": "18117047", "Name:": "KSHITIJ SRIKANT", "Company:": "Google Hardware", "Course:": "B.Tech.", "Accepted:": "Yes "}, {"Enrollment no:": "18116055", "Name:": "NIKHIL CHOUDHARY", "Company:": "American Express (Technology)", "Course:": "B.Tech.", "Accepted:": "Yes "}, {"Enrollment no:": "18116062", "Name:": "PRANAV SINGHAL", "Company:": "Goldman Sachs Services Private Ltd.", "Course:": "B.Tech.", "Accepted:": "Yes "}, {"Enrollment no:": "18116067", "Name:": "SAKSHAM SHARMA", "Company:": "Microsoft India Pvt. Ltd. (SE)", "Course:": "B.Tech.", "Accepted:": "Yes "}, {"Enrollment no:": "18116070", "Name:": "SANSKAR AGARWAL", "Company:": "Microsoft India Pvt. Ltd. (SE)", "Course:": "B.Tech.", "Accepted:": "Yes "}, {"Enrollment no:": "18115105", "Name:": "SPARSH GUPTA", "Company:": "American Express (Technology)", "Course:": "B.Tech.", "Accepted:": "Yes "}, {"Enrollment no:": "18116079", "Name:": "TANYA KUMARI", "Company:": "American Express (Technology)", "Course:": "B.Tech.", "Accepted:": "Yes "}, {"Enrollment no:": "18116080", "Name:": "UMAMA ALIM", "Company:": "Goldman Sachs Services Private Ltd.", "Course:": "B.Tech.", "Accepted:": "Yes "}, {"Enrollment no:": "18116081", "Name:": "VANSHIKA SINGH", "Company:": "Goldman Sachs Services Private Ltd.", "Course:": "B.Tech.", "Accepted:": "Yes "}, {"Enrollment no:": "18117112", "Name:": "VANSHIKA VIPIN BHARGAVA", "Company:": "Google SWE", "Course:": "B.Tech.", "Accepted:": "Yes "}, {"Enrollment no:": "18117112", "Name:": "VANSHIKA VIPIN BHARGAVA", "Company:": "Goldman Sachs Services Private Ltd.", "Course:": "B.Tech.", "Accepted:": "No"}], "EPH": [{"Enrollment no:": "18122009", "Name:": "KALPTARU AGARWAL", "Company:": "Uber", "Course:": "B.Tech.", "Accepted:": "Yes "}, {"Enrollment no:": "18122013", "Name:": "MOHIT SHARMA", "Company:": "Microsoft (PIO)", "Course:": "B.Tech.", "Accepted:": "Yes "}], "GT": [{"Enrollment no:": "17410009", "Name:": "GOURANSHI CHOUDHARY", "Company:": "Sprinklr(Product Designer)", "Course:": "IMT", "Accepted:": "Yes "}, {"Enrollment no:": "17121032", "Name:": "VISHWAJEET SINGH BHADOURIA", "Company:": "Sprinklr(Product Designer)", "Course:": "IMT", "Accepted:": "Yes "}], "GPT": [{"Enrollment no:": "17411001", "Name:": "ADITHYA SHASHIDHARA SHETTAR", "Company:": "Goldman Sachs Services Private Ltd.", "Course:": "IMT", "Accepted:": "Yes "}], "ME": [{"Enrollment no:": "18117011", "Name:": "AMOGH TANDON", "Company:": "ITC", "Course:": "B.Tech.", "Accepted:": "Yes "}, {"Enrollment no:": "18118014", "Name:": "ARPIT KHANDELWAL", "Company:": "American Express (Analytics)", "Course:": "B.Tech.", "Accepted:": "Yes "}, {"Enrollment no:": "18117040", "Name:": "ISSHITA", "Company:": "ITC", "Course:": "B.Tech.", "Accepted:": "Yes "}, {"Enrollment no:": "18117051", "Name:": "MAHEK RAINA", "Company:": "Hindustan Unilever Limited", "Course:": "B.Tech.", "Accepted:": "Yes "}, {"Enrollment no:": "18117053", "Name:": "MANAS CHAUDHARY", "Company:": "Microsoft (PIO)", "Course:": "B.Tech.", "Accepted:": "Yes "}, {"Enrollment no:": "18117065", "Name:": "NOOR NISHA", "Company:": "Hindustan Unilever Limited", "Course:": "B.Tech.", "Accepted:": "Yes "}, {"Enrollment no:": "18117096", "Name:": "SHANU KHANDELWAL", "Company:": "JP Morgan QR (PIO)", "Course:": "B.Tech.", "Accepted:": "Yes "}, {"Enrollment no:": "18118069", "Name:": "SOUMYAJEET JAISWAL", "Company:": "Hindustan Unilever Limited", "Course:": "B.Tech.", "Accepted:": "Yes "}], "IN": [{"Enrollment no:": "18119005", "Name:": "ADITYA KUMAR SRIVASTAVA", "Company:": "Microsoft India Pvt. Ltd. (SE)", "Course:": "B.Tech.", "Accepted:": "Yes "}, {"Enrollment no:": "18119034", "Name:": "SEJAL GUPTA", "Company:": "American Express (Analytics)", "Course:": "B.Tech.", "Accepted:": "Yes "}, {"Enrollment no:": "18119043", "Name:": "VIPUL BANSAL", "Company:": "American Express (Analytics)", "Course:": "B.Tech.", "Accepted:": "Yes "}]}