{"MES": [{"Enrollment no:": "19612015", "Name:": "VANIKA VERMA", "Company:": "Vedanta Oil & Gas", "Course:": "MSc", "Accepted:": "Yes "}], "MSM": [{"Enrollment no:": "16312003", "Name:": "ANKIT CHAWLA", "Company:": "Goldman Sachs", "Course:": "IMSc", "Accepted:": "Yes "}, {"Enrollment no:": "16312004", "Name:": "ANSHUL AGRAWAL", "Company:": "Samsung R&D Bangalore", "Course:": "IMSc", "Accepted:": "Yes "}, {"Enrollment no:": "16312005", "Name:": "ANSHUL GOYAL", "Company:": "Uber India System Pvt Ltd.", "Course:": "IMSc", "Accepted:": "Yes "}, {"Enrollment no:": "16312006", "Name:": "ASHISH RANJAN", "Company:": "Goldman Sachs", "Course:": "IMSc", "Accepted:": "Yes "}, {"Enrollment no:": "16312007", "Name:": "AYUSHI JAISWAL", "Company:": "Adobe Systems", "Course:": "IMSc", "Accepted:": "Yes "}, {"Enrollment no:": "16312008", "Name:": "BAJRANG", "Company:": "Publicis Sapient [PE]", "Course:": "IMSc", "Accepted:": "Yes "}, {"Enrollment no:": "16312009", "Name:": "BENDKHALE AMIT CHANDRASHEKHAR", "Company:": "Myntra", "Course:": "IMSc", "Accepted:": "Yes "}, {"Enrollment no:": "16312012", "Name:": "HARSH NANDWANA", "Company:": "Societe Generale", "Course:": "IMSc", "Accepted:": "Yes "}, {"Enrollment no:": "16312013", "Name:": "HARSHIT GARG", "Company:": "AQR Capital India Services LLP", "Course:": "IMSc", "Accepted:": "Yes "}, {"Enrollment no:": "16312013", "Name:": "HARSHIT GARG", "Company:": "Nutanix", "Course:": "IMSc", "Accepted:": "No"}, {"Enrollment no:": "16312014", "Name:": "KASHISH VERMA", "Company:": "NoBroker[Software Development Intern]", "Course:": "IMSc", "Accepted:": "Yes "}, {"Enrollment no:": "16312015", "Name:": "LAXMIKANT MISHRA", "Company:": "Adobe Systems (Direct Offer)", "Course:": "IMSc", "Accepted:": "Yes "}, {"Enrollment no:": "16118049", "Name:": "MALPURE AKASH CHANDRAKANT", "Company:": "Samsung R&D Bangalore", "Course:": "IMSc", "Accepted:": "Yes "}, {"Enrollment no:": "16312016", "Name:": "MANAS GUPTA", "Company:": "Sprinklr India Pvt. Ltd.", "Course:": "IMSc", "Accepted:": "No"}, {"Enrollment no:": "16312016", "Name:": "MANAS GUPTA", "Company:": "D E Shaw India Pvt. Ltd.", "Course:": "IMSc", "Accepted:": "No"}, {"Enrollment no:": "16312016", "Name:": "MANAS GUPTA", "Company:": "JP Morgan Chase & Co (Quant)", "Course:": "IMSc", "Accepted:": "Yes "}, {"Enrollment no:": "16312016", "Name:": "MANAS GUPTA", "Company:": "Adobe Systems (Direct Offer)", "Course:": "IMSc", "Accepted:": "No"}, {"Enrollment no:": "16312017", "Name:": "MOHIT SINGH PANWAR", "Company:": "KnowDis Data Science LLP", "Course:": "IMSc", "Accepted:": "Yes "}, {"Enrollment no:": "16118063", "Name:": "PRIYANSHU KUMAR SAH", "Company:": "Auro Sundram Ply & Door (JV of centuryply)", "Course:": "IMSc", "Accepted:": "Yes "}, {"Enrollment no:": "16312020", "Name:": "RITESH KUMAR SINGH", "Company:": "Envestnet Yodlee", "Course:": "IMSc", "Accepted:": "Yes "}, {"Enrollment no:": "16312021", "Name:": "SAGAR SHUKLA", "Company:": "Intuit", "Course:": "IMSc", "Accepted:": "Yes "}, {"Enrollment no:": "16312021", "Name:": "SAGAR SHUKLA", "Company:": "Amazon", "Course:": "IMSc", "Accepted:": "No"}, {"Enrollment no:": "16312023", "Name:": "SANTOSH KUMAR MEENA", "Company:": "Samsung R & D Institute Noida", "Course:": "IMSc", "Accepted:": "Yes "}, {"Enrollment no:": "16312024", "Name:": "SHIVANSH ARORA", "Company:": "Flipkart", "Course:": "IMSc", "Accepted:": "Yes "}, {"Enrollment no:": "16312025", "Name:": "SIDHARTH KUMAR", "Company:": "Doubtnut", "Course:": "IMSc", "Accepted:": "Yes "}, {"Enrollment no:": "16312026", "Name:": "SNEHA MAHESHWARI", "Company:": "American Express (Analytics)", "Course:": "IMSc", "Accepted:": "Yes "}, {"Enrollment no:": "16312028", "Name:": "TUSHAR KUMAWAT", "Company:": "Myntra", "Course:": "IMSc", "Accepted:": "Yes "}, {"Enrollment no:": "16312029", "Name:": "UDIT KALANI", "Company:": "Adobe Systems (Direct Offer)", "Course:": "IMSc", "Accepted:": "Yes "}], "AR": [{"Enrollment no:": "16110025", "Name:": "RUCHI AWASTHI", "Company:": "HyperVerge", "Course:": "B.Arch.", "Accepted:": "Yes "}], "BT": [{"Enrollment no:": "17111013", "Name:": "DHRUV KALSOTRA", "Company:": "KnowDis Data Science LLP", "Course:": "B.Tech.", "Accepted:": "Yes "}, {"Enrollment no:": "17111017", "Name:": "MANSHISH AGRAWAL", "Company:": "Standard Chartered ", "Course:": "B.Tech.", "Accepted:": "Yes "}, {"Enrollment no:": "17111026", "Name:": "RIKOV BHATTACHARYA", "Company:": "KPIT Technologies Ltd", "Course:": "B.Tech.", "Accepted:": "Yes "}], "CH": [{"Enrollment no:": "17112002", "Name:": "ABDULAHAD RAFIUDDIN KHAN", "Company:": "JP Morgan Chase & Co (Software)", "Course:": "B.Tech.", "Accepted:": "Yes "}, {"Enrollment no:": "17112003", "Name:": "ABHIJEET RATHI", "Company:": "Standard Chartered ", "Course:": "B.Tech.", "Accepted:": "Yes "}, {"Enrollment no:": "17112007", "Name:": "ABHISHEK KUMAR PAL", "Company:": "Inspilearn Education Pvt. Ltd. (Scholr)", "Course:": "B.Tech.", "Accepted:": "Yes "}, {"Enrollment no:": "17112016", "Name:": "ASHISH KUMAR SINGH", "Company:": "Droom (All Profiles)", "Course:": "B.Tech.", "Accepted:": "Yes "}, {"Enrollment no:": "17112019", "Name:": "AYUSH JUYAL", "Company:": "Reliance Industries Limited", "Course:": "B.Tech.", "Accepted:": "Yes "}, {"Enrollment no:": "17112024", "Name:": "DISHA BHATIA", "Company:": "Hindustan Unilever Limited", "Course:": "B.Tech.", "Accepted:": "Yes "}, {"Enrollment no:": "17112027", "Name:": "DIVYANSH JOSHI", "Company:": "Axxela Advisory Services", "Course:": "B.Tech.", "Accepted:": "Yes "}, {"Enrollment no:": "17112033", "Name:": "HIMANSHU", "Company:": "Udaan.com [BD]", "Course:": "B.Tech.", "Accepted:": "Yes "}, {"Enrollment no:": "17112036", "Name:": "KARTHIK RAMESH IYER", "Company:": "JP Morgan Chase & Co (Software)", "Course:": "B.Tech.", "Accepted:": "Yes "}, {"Enrollment no:": "17112037", "Name:": "KAUSTUBH MAHESHWARI", "Company:": "Reliance Industries Limited", "Course:": "B.Tech.", "Accepted:": "Yes "}, {"Enrollment no:": "17112045", "Name:": "MUSKAN GARG", "Company:": "Hindustan Unilever Limited", "Course:": "B.Tech.", "Accepted:": "Yes "}, {"Enrollment no:": "17112049", "Name:": "NISHA", "Company:": "HSBC (India)", "Course:": "B.Tech.", "Accepted:": "Yes "}, {"Enrollment no:": "17118050", "Name:": "PRAKHAR AGARWAL", "Company:": "JP Morgan Chase & Co (Software)", "Course:": "B.Tech.", "Accepted:": "Yes "}, {"Enrollment no:": "17121019", "Name:": "PRANAV GUPTA", "Company:": "Futures First", "Course:": "B.Tech.", "Accepted:": "Yes "}, {"Enrollment no:": "17112056", "Name:": "PULKIT SHARMA", "Company:": "Optum", "Course:": "B.Tech.", "Accepted:": "Yes "}, {"Enrollment no:": "17112058", "Name:": "RAHUL GARG", "Company:": "Standard Chartered ", "Course:": "B.Tech.", "Accepted:": "Yes "}, {"Enrollment no:": "17112059", "Name:": "RAHUL GOYAL", "Company:": "Futures First", "Course:": "B.Tech.", "Accepted:": "Yes "}, {"Enrollment no:": "17112065", "Name:": "RISHABH SOOD", "Company:": "Reliance Industries Limited", "Course:": "B.Tech.", "Accepted:": "Yes "}, {"Enrollment no:": "17112067", "Name:": "RITIK GUPTA", "Company:": "GE Digital", "Course:": "B.Tech.", "Accepted:": "Yes "}, {"Enrollment no:": "17112068", "Name:": "RIYA BANSAL", "Company:": "Goldman Sachs", "Course:": "B.Tech.", "Accepted:": "Yes "}, {"Enrollment no:": "17112069", "Name:": "SAMRUDDHI AJAYKUMAR MANE", "Company:": "Microsoft (PIO)", "Course:": "B.Tech.", "Accepted:": "Yes "}, {"Enrollment no:": "17112073", "Name:": "SHIVANI RAGHUWANSHI", "Company:": "Citibank India", "Course:": "B.Tech.", "Accepted:": "Yes "}, {"Enrollment no:": "17112075", "Name:": "SHUBHAM SINGH DANGI", "Company:": "Reliance Industries Limited", "Course:": "B.Tech.", "Accepted:": "Yes "}, {"Enrollment no:": "17112081", "Name:": "SWARNIMA DHABRIYA", "Company:": "Innovaccer (SummerGeeks 2020)", "Course:": "B.Tech.", "Accepted:": "Yes "}, {"Enrollment no:": "17121027", "Name:": "SWAYAMJEET SWAIN", "Company:": "TMI Network", "Course:": "B.Tech.", "Accepted:": "Yes "}, {"Enrollment no:": "17112084", "Name:": "UDISHA DUBEY", "Company:": "Goldman Sachs", "Course:": "B.Tech.", "Accepted:": "Yes "}, {"Enrollment no:": "17112085", "Name:": "UTKARSH MISHRA", "Company:": "Droom (All Profiles)", "Course:": "B.Tech.", "Accepted:": "Yes "}, {"Enrollment no:": "17112086", "Name:": "VAIBHAV PIPARA", "Company:": "EXL Service", "Course:": "B.Tech.", "Accepted:": "Yes "}, {"Enrollment no:": "17112087", "Name:": "VASAV BANSAL", "Company:": "Vedanta Oil & Gas", "Course:": "B.Tech.", "Accepted:": "Yes "}, {"Enrollment no:": "17112088", "Name:": "VINAY JAIN", "Company:": "Next Education India Pvt. Ltd.", "Course:": "B.Tech.", "Accepted:": "No"}], "CE": [{"Enrollment no:": "17113001", "Name:": "ABHINAV", "Company:": "Consulting Engineers Group Limited", "Course:": "B.Tech.", "Accepted:": "Yes "}, {"Enrollment no:": "17113008", "Name:": "AKHILESH SIROHI", "Company:": "NoBroker[Software Development Intern]", "Course:": "B.Tech.", "Accepted:": "Yes "}, {"Enrollment no:": "17113013", "Name:": "ANKIT GARG", "Company:": "Futures First", "Course:": "B.Tech.", "Accepted:": "Yes "}, {"Enrollment no:": "17113022", "Name:": "ATUL GARG", "Company:": "Publicis Sapient [PE]", "Course:": "B.Tech.", "Accepted:": "Yes "}, {"Enrollment no:": "17113024", "Name:": "AYUSH DHAKA", "Company:": "EXL Service", "Course:": "B.Tech.", "Accepted:": "Yes "}, {"Enrollment no:": "17113029", "Name:": "CHANDNI BENIWAL", "Company:": "Citibank India", "Course:": "B.Tech.", "Accepted:": "Yes "}, {"Enrollment no:": "17113036", "Name:": "DIVYANSH JINDAL", "Company:": "Udaan.com [BD]", "Course:": "B.Tech.", "Accepted:": "Yes "}, {"Enrollment no:": "17113045", "Name:": "HIMMAT SINGH", "Company:": "Doubtnut", "Course:": "B.Tech.", "Accepted:": "Yes "}, {"Enrollment no:": "17113049", "Name:": "JAY MODI", "Company:": "Udaan.com [BD]", "Course:": "B.Tech.", "Accepted:": "Yes "}, {"Enrollment no:": "17113051", "Name:": "KARTIK JOSHI", "Company:": "Goldman Sachs", "Course:": "B.Tech.", "Accepted:": "Yes "}, {"Enrollment no:": "17113052", "Name:": "KESHAV", "Company:": "Consulting Engineers Group Limited", "Course:": "B.Tech.", "Accepted:": "Yes "}, {"Enrollment no:": "17113054", "Name:": "KRISHNANAND RAI", "Company:": "Auro Sundram Ply & Door (JV of centuryply)", "Course:": "B.Tech.", "Accepted:": "Yes "}, {"Enrollment no:": "17113057", "Name:": "KUNAL KUMAR", "Company:": "Fidelity Investments", "Course:": "B.Tech.", "Accepted:": "Yes "}, {"Enrollment no:": "17113061", "Name:": "MANISH KUMAR SHARMA", "Company:": "Standard Chartered ", "Course:": "B.Tech.", "Accepted:": "Yes "}, {"Enrollment no:": "17113067", "Name:": "MOHD SHADAB SIDDIQUI", "Company:": "Futures First", "Course:": "B.Tech.", "Accepted:": "Yes "}, {"Enrollment no:": "17113076", "Name:": "NIKHIL RAIZADA", "Company:": "Udaan.com [BD]", "Course:": "B.Tech.", "Accepted:": "Yes "}, {"Enrollment no:": "17113077", "Name:": "NIKITA SINGH", "Company:": "Vedanta Oil & Gas", "Course:": "B.Tech.", "Accepted:": "Yes "}, {"Enrollment no:": "17113082", "Name:": "PARAS SINGH RAJPUT", "Company:": "Innovaccer (SummerGeeks 2020)", "Course:": "B.Tech.", "Accepted:": "Yes "}, {"Enrollment no:": "17113087", "Name:": "PRAKASH CHAND", "Company:": "Doubtnut", "Course:": "B.Tech.", "Accepted:": "Yes "}, {"Enrollment no:": "17113092", "Name:": "PRATYUSH SINHA", "Company:": "GE Digital", "Course:": "B.Tech.", "Accepted:": "Yes "}, {"Enrollment no:": "17113093", "Name:": "PRITHA HOWLADAR", "Company:": "Citibank India", "Course:": "B.Tech.", "Accepted:": "Yes "}, {"Enrollment no:": "17113094", "Name:": "PULKIT KHANNA", "Company:": "EXL Service", "Course:": "B.Tech.", "Accepted:": "Yes "}, {"Enrollment no:": "17113100", "Name:": "RITIK KUMAR KHATRI", "Company:": "Standard Chartered ", "Course:": "B.Tech.", "Accepted:": "Yes "}, {"Enrollment no:": "17113102", "Name:": "ROHIT SINGH", "Company:": "ReachIvy.com (Business Development)", "Course:": "B.Tech.", "Accepted:": "Yes "}, {"Enrollment no:": "17113105", "Name:": "SAKSHI GUPTA", "Company:": "Microsoft (PIO)", "Course:": "B.Tech.", "Accepted:": "Yes "}, {"Enrollment no:": "17113113", "Name:": "SHREY MADAAN", "Company:": "Droom (All Profiles)", "Course:": "B.Tech.", "Accepted:": "Yes "}, {"Enrollment no:": "17113116", "Name:": "SIDDHARTH VARSHNEY", "Company:": "Publicis Sapient [PE]", "Course:": "B.Tech.", "Accepted:": "Yes "}, {"Enrollment no:": "17118077", "Name:": "VAIBHAV", "Company:": "Goldman Sachs", "Course:": "B.Tech.", "Accepted:": "Yes "}, {"Enrollment no:": "17113121", "Name:": "VAIBHAV BANSAL", "Company:": "NoBroker [Business Consultant]", "Course:": "B.Tech.", "Accepted:": "Yes "}, {"Enrollment no:": "17113131", "Name:": "VISHWAS RAWAT", "Company:": "Standard Chartered ", "Course:": "B.Tech.", "Accepted:": "Yes "}, {"Enrollment no:": "17113132", "Name:": "YASH AGARWAL", "Company:": "American Express (Analytics)", "Course:": "B.Tech.", "Accepted:": "Yes "}], "CSAE": [{"Enrollment no:": "19535001", "Name:": "ABHILASH PATHAK", "Company:": "Cisco Systems", "Course:": "M.Tech.", "Accepted:": "Yes "}, {"Enrollment no:": "19535003", "Name:": "AKANKSHA KUMARI", "Company:": "IBM Research & Extreme Blue Internship", "Course:": "M.Tech.", "Accepted:": "Yes "}, {"Enrollment no:": "19535004", "Name:": "AMAN JAIN", "Company:": "Tata Consultancy Sevices Limited", "Course:": "M.Tech.", "Accepted:": "Yes "}, {"Enrollment no:": "19535007", "Name:": "ANUPAMA BISWAS", "Company:": "Samsung R&D Bangalore", "Course:": "M.Tech.", "Accepted:": "Yes "}, {"Enrollment no:": "19535009", "Name:": "BHOSLE RUSHIKESH SHAMRAO", "Company:": "Microsoft (Software)", "Course:": "M.Tech.", "Accepted:": "Yes "}, {"Enrollment no:": "19535010", "Name:": "CHAUDHARI SUSHMEN KAILAS MEENAKSHI", "Company:": "Samsung R&D Bangalore", "Course:": "M.Tech.", "Accepted:": "Yes "}, {"Enrollment no:": "19535012", "Name:": "DEEPAK VERMA", "Company:": "Cisco Systems", "Course:": "M.Tech.", "Accepted:": "Yes "}, {"Enrollment no:": "19535013", "Name:": "DEEPENDRA SINGH CHOUHAN", "Company:": "Service now", "Course:": "M.Tech.", "Accepted:": "Yes "}, {"Enrollment no:": "19535019", "Name:": "MINI AGARWAL", "Company:": "Samsung R&D Bangalore", "Course:": "M.Tech.", "Accepted:": "Yes "}, {"Enrollment no:": "19535023", "Name:": "PATEL SHREYAS RAMESHBHAI", "Company:": "Samsung Semiconductor (SW)", "Course:": "M.Tech.", "Accepted:": "Yes "}, {"Enrollment no:": "19535024", "Name:": "RAJPUROHIT AJAY SINGH BAGH SINGH", "Company:": "PayU", "Course:": "M.Tech.", "Accepted:": "Yes "}], "CSE": [{"Enrollment no:": "17114001", "Name:": "AARYAN JAIN", "Company:": "Sprinklr India Pvt. Ltd.", "Course:": "B.Tech.", "Accepted:": "Yes "}, {"Enrollment no:": "17114002", "Name:": "ABHIJEET SHAKYA", "Company:": "Oracle India Pvt. Ltd.", "Course:": "B.Tech.", "Accepted:": "Yes "}, {"Enrollment no:": "17114004", "Name:": "ABHISHEK JITENDRA RATHOD", "Company:": "Goldman Sachs", "Course:": "B.Tech.", "Accepted:": "Yes "}, {"Enrollment no:": "17114005", "Name:": "ABHISHEK KUMAR", "Company:": "Goldman Sachs", "Course:": "B.Tech.", "Accepted:": "Yes "}, {"Enrollment no:": "17118007", "Name:": "AJAY N", "Company:": "Microsoft (Software)", "Course:": "B.Tech.", "Accepted:": "Yes "}, {"Enrollment no:": "17114008", "Name:": "AMAN JAISWAL", "Company:": "Amazon", "Course:": "B.Tech.", "Accepted:": "Yes "}, {"Enrollment no:": "17114009", "Name:": "AMAN VERMA", "Company:": "American Express (Technology)", "Course:": "B.Tech.", "Accepted:": "Yes "}, {"Enrollment no:": "17114011", "Name:": "ANIKET GOYAL", "Company:": "Sprinklr India Pvt. Ltd.", "Course:": "B.Tech.", "Accepted:": "Yes "}, {"Enrollment no:": "17114013", "Name:": "ANSHUMAN SHAKYA", "Company:": "JP Morgan Chase & Co (Software)", "Course:": "B.Tech.", "Accepted:": "Yes "}, {"Enrollment no:": "17114015", "Name:": "ASHUTOSH CHAUBEY", "Company:": "Adobe Systems (Direct Offer)", "Course:": "B.Tech.", "Accepted:": "Yes "}, {"Enrollment no:": "17114017", "Name:": "AYUSH AGARWAL", "Company:": "Adobe Systems (Direct Offer)", "Course:": "B.Tech.", "Accepted:": "Yes "}, {"Enrollment no:": "17114019", "Name:": "BHANU PRATAP", "Company:": "Salesforce.com Pvt Ltd ", "Course:": "B.Tech.", "Accepted:": "Yes "}, {"Enrollment no:": "17114020", "Name:": "BHAVYE JAIN", "Company:": "Microsoft (Software)", "Course:": "B.Tech.", "Accepted:": "Yes "}, {"Enrollment no:": "17114021", "Name:": "BHIMAVARAPU SASI KIRAN REDDY", "Company:": "AQR Capital India Services LLP", "Course:": "B.Tech.", "Accepted:": "Yes "}, {"Enrollment no:": "17114022", "Name:": "CHIRAG DALMIA", "Company:": "American Express (Analytics)", "Course:": "B.Tech.", "Accepted:": "Yes "}, {"Enrollment no:": "17114023", "Name:": "DAVID GOKIMMUNG", "Company:": "Oracle India Pvt. Ltd.", "Course:": "B.Tech.", "Accepted:": "Yes "}, {"Enrollment no:": "17114024", "Name:": "DEEPANSH NAGARIA", "Company:": "A.P.T Portfolio", "Course:": "B.Tech.", "Accepted:": "Yes "}, {"Enrollment no:": "17114024", "Name:": "DEEPANSH NAGARIA", "Company:": "Nutanix", "Course:": "B.Tech.", "Accepted:": "No"}, {"Enrollment no:": "17114025", "Name:": "DEEPIKA CHOUDHARY", "Company:": "Microsoft (Software)", "Course:": "B.Tech.", "Accepted:": "Yes "}, {"Enrollment no:": "17114027", "Name:": "DIVYANSHU SALVE", "Company:": "BNY Mellon Technology", "Course:": "B.Tech.", "Accepted:": "Yes "}, {"Enrollment no:": "17114028", "Name:": "GAGAN KUMRE", "Company:": "Citibank India", "Course:": "B.Tech.", "Accepted:": "Yes "}, {"Enrollment no:": "17114029", "Name:": "GANDHI RONNIE", "Company:": "Microsoft (PIO)", "Course:": "B.Tech.", "Accepted:": "Yes "}, {"Enrollment no:": "17114030", "Name:": "GANGAVARAPU SURESH BABU", "Company:": "Intuit", "Course:": "B.Tech.", "Accepted:": "Yes "}, {"Enrollment no:": "17114030", "Name:": "GANGAVARAPU SURESH BABU", "Company:": "Amazon", "Course:": "B.Tech.", "Accepted:": "No"}, {"Enrollment no:": "17114031", "Name:": "GATTUKINDI VISHNUTEJA", "Company:": "Samsung R&D Bangalore", "Course:": "B.Tech.", "Accepted:": "Yes "}, {"Enrollment no:": "17114032", "Name:": "GAURAV DEWAT", "Company:": "Amazon", "Course:": "B.Tech.", "Accepted:": "Yes "}, {"Enrollment no:": "17114033", "Name:": "GHETIA SIDDHARTH", "Company:": "Adobe Systems (Direct Offer)", "Course:": "B.Tech.", "Accepted:": "Yes "}, {"Enrollment no:": "17114034", "Name:": "GODDU VISHAL", "Company:": "Goldman Sachs", "Course:": "B.Tech.", "Accepted:": "Yes "}, {"Enrollment no:": "17114036", "Name:": "HARSH KUMAR BHARTIYA", "Company:": "Sprinklr India Pvt. Ltd.", "Course:": "B.Tech.", "Accepted:": "No"}, {"Enrollment no:": "17114036", "Name:": "HARSH KUMAR BHARTIYA", "Company:": "Adobe Systems (Direct Offer)", "Course:": "B.Tech.", "Accepted:": "No"}, {"Enrollment no:": "17114036", "Name:": "HARSH KUMAR BHARTIYA", "Company:": "Tower Research Capital", "Course:": "B.Tech.", "Accepted:": "Yes "}, {"Enrollment no:": "17114036", "Name:": "HARSH KUMAR BHARTIYA", "Company:": "D E Shaw India Pvt. Ltd.", "Course:": "B.Tech.", "Accepted:": "No"}, {"Enrollment no:": "17114037", "Name:": "HARSHIT MAURYA", "Company:": "Salesforce.com Pvt Ltd ", "Course:": "B.Tech.", "Accepted:": "Yes "}, {"Enrollment no:": "17114038", "Name:": "HEMANT SINGH", "Company:": "Samsung R&D Bangalore", "Course:": "B.Tech.", "Accepted:": "Yes "}, {"Enrollment no:": "17114039", "Name:": "HRITVI NARENDRA BHANDARI", "Company:": "Goldman Sachs", "Course:": "B.Tech.", "Accepted:": "No"}, {"Enrollment no:": "17114039", "Name:": "HRITVI NARENDRA BHANDARI", "Company:": "Uber India System Pvt Ltd.", "Course:": "B.Tech.", "Accepted:": "Yes "}, {"Enrollment no:": "17114041", "Name:": "KALE MAHESH JYOTIBA", "Company:": "Oracle India Pvt. Ltd.", "Course:": "B.Tech.", "Accepted:": "No"}, {"Enrollment no:": "17114041", "Name:": "KALE MAHESH JYOTIBA", "Company:": "Schlumberger software", "Course:": "B.Tech.", "Accepted:": "Yes "}, {"Enrollment no:": "17114043", "Name:": "KARAN LAMBA", "Company:": "Flipkart", "Course:": "B.Tech.", "Accepted:": "Yes "}, {"Enrollment no:": "17114044", "Name:": "KAUSTUBH TRIVEDI", "Company:": "Goldman Sachs", "Course:": "B.Tech.", "Accepted:": "Yes "}, {"Enrollment no:": "17114044", "Name:": "KAUSTUBH TRIVEDI", "Company:": "American Express (Technology)", "Course:": "B.Tech.", "Accepted:": "No"}, {"Enrollment no:": "17114045", "Name:": "KESIREDDY SHIVA REDDY", "Company:": "Samsung R&D Bangalore", "Course:": "B.Tech.", "Accepted:": "Yes "}, {"Enrollment no:": "17114047", "Name:": "LAKKI REDDY HARSHAVARDHAN REDDY", "Company:": "PayU", "Course:": "B.Tech.", "Accepted:": "Yes "}, {"Enrollment no:": "17114048", "Name:": "MANSI AGARWAL", "Company:": "Adobe Systems (Direct Offer)", "Course:": "B.Tech.", "Accepted:": "Yes "}, {"Enrollment no:": "17114049", "Name:": "MULA RAM", "Company:": "Rupeek (SDE)", "Course:": "B.Tech.", "Accepted:": "Yes "}, {"Enrollment no:": "17114053", "Name:": "OMMI AKASH", "Company:": "TCS", "Course:": "B.Tech.", "Accepted:": "Yes "}, {"Enrollment no:": "17114054", "Name:": "PARVATHA SAI KRISHNA ABHIRAM", "Company:": "Nutanix", "Course:": "B.Tech.", "Accepted:": "Yes "}, {"Enrollment no:": "17114055", "Name:": "PEDDI KRISHNA YESWANTH", "Company:": "OLA Cabs (Research Engineer)", "Course:": "B.Tech.", "Accepted:": "Yes "}, {"Enrollment no:": "17114057", "Name:": "PIYUSH SETHIA", "Company:": "Uber India System Pvt Ltd.", "Course:": "B.Tech.", "Accepted:": "No"}, {"Enrollment no:": "17114057", "Name:": "PIYUSH SETHIA", "Company:": "Tower Research Capital", "Course:": "B.Tech.", "Accepted:": "Yes "}, {"Enrollment no:": "17114057", "Name:": "PIYUSH SETHIA", "Company:": "Sprinklr India Pvt. Ltd.", "Course:": "B.Tech.", "Accepted:": "No"}, {"Enrollment no:": "17114057", "Name:": "PIYUSH SETHIA", "Company:": "D E Shaw India Pvt. Ltd.", "Course:": "B.Tech.", "Accepted:": "No"}, {"Enrollment no:": "17114057", "Name:": "PIYUSH SETHIA", "Company:": "Tata Consultancy Sevices Limited", "Course:": "B.Tech.", "Accepted:": "No"}, {"Enrollment no:": "17114057", "Name:": "PIYUSH SETHIA", "Company:": "Google (Software)", "Course:": "B.Tech.", "Accepted:": "No"}, {"Enrollment no:": "17114057", "Name:": "PIYUSH SETHIA", "Company:": "Adobe Systems (Direct Offer)", "Course:": "B.Tech.", "Accepted:": "No"}, {"Enrollment no:": "17114059", "Name:": "PRATEEK MALI", "Company:": "Samsung Semiconductor (SW)", "Course:": "B.Tech.", "Accepted:": "Yes "}, {"Enrollment no:": "17114060", "Name:": "PULKIT MOHARSINGH JEPH", "Company:": "Fidelity Investments", "Course:": "B.Tech.", "Accepted:": "Yes "}, {"Enrollment no:": "17114061", "Name:": "RAHUL DUGAR", "Company:": "Sprinklr India Pvt. Ltd.", "Course:": "B.Tech.", "Accepted:": "No"}, {"Enrollment no:": "17114061", "Name:": "RAHUL DUGAR", "Company:": "Google (Software)", "Course:": "B.Tech.", "Accepted:": "No"}, {"Enrollment no:": "17114061", "Name:": "RAHUL DUGAR", "Company:": "Tower Research Capital", "Course:": "B.Tech.", "Accepted:": "Yes "}, {"Enrollment no:": "17114061", "Name:": "RAHUL DUGAR", "Company:": "D E Shaw India Pvt. Ltd.", "Course:": "B.Tech.", "Accepted:": "No"}, {"Enrollment no:": "17114062", "Name:": "RAHUL GOME", "Company:": "Salesforce.com Pvt Ltd ", "Course:": "B.Tech.", "Accepted:": "Yes "}, {"Enrollment no:": "17114063", "Name:": "RITIK KUMAR", "Company:": "Microsoft (Software)", "Course:": "B.Tech.", "Accepted:": "Yes "}, {"Enrollment no:": "17114066", "Name:": "ROODRAM PANERI", "Company:": "Adobe Systems (Direct Offer)", "Course:": "B.Tech.", "Accepted:": "Yes "}, {"Enrollment no:": "17114067", "Name:": "SAMEER GUPTA", "Company:": "Schlumberger software", "Course:": "B.Tech.", "Accepted:": "Yes "}, {"Enrollment no:": "17114067", "Name:": "SAMEER GUPTA", "Company:": "Oracle India Pvt. Ltd.", "Course:": "B.Tech.", "Accepted:": "No"}, {"Enrollment no:": "17114068", "Name:": "SAURABH SINGH", "Company:": "Tower Research Capital", "Course:": "B.Tech.", "Accepted:": "Yes "}, {"Enrollment no:": "17114069", "Name:": "SAURABH SINGH GAUTAM", "Company:": "American Express (Technology)", "Course:": "B.Tech.", "Accepted:": "Yes "}, {"Enrollment no:": "17114070", "Name:": "SHASHANK KASHYAP", "Company:": "Cisco Systems", "Course:": "B.Tech.", "Accepted:": "Yes "}, {"Enrollment no:": "17115088", "Name:": "SHIVANSH BINDAL", "Company:": "Adobe Systems (Direct Offer)", "Course:": "B.Tech.", "Accepted:": "Yes "}, {"Enrollment no:": "17114071", "Name:": "SIDDHANT NAYAK", "Company:": "Amazon", "Course:": "B.Tech.", "Accepted:": "Yes "}, {"Enrollment no:": "17114073", "Name:": "THEEGALA LOKESH REDDY", "Company:": "Nutanix", "Course:": "B.Tech.", "Accepted:": "Yes "}, {"Enrollment no:": "17114073", "Name:": "THEEGALA LOKESH REDDY", "Company:": "A.P.T Portfolio", "Course:": "B.Tech.", "Accepted:": "No"}, {"Enrollment no:": "17114074", "Name:": "TWARIT WAIKAR", "Company:": "Salesforce.com Pvt Ltd ", "Course:": "B.Tech.", "Accepted:": "Yes "}, {"Enrollment no:": "17114075", "Name:": "VED ATUL TAMBAT", "Company:": "Amazon", "Course:": "B.Tech.", "Accepted:": "Yes "}, {"Enrollment no:": "17114076", "Name:": "VISHAL GARG", "Company:": "Microsoft (Software)", "Course:": "B.Tech.", "Accepted:": "Yes "}], "EE": [{"Enrollment no:": "17115001", "Name:": "ABHINAV BYAHUT", "Company:": "AppDynamics India Pvt Ltd", "Course:": "B.Tech.", "Accepted:": "No"}, {"Enrollment no:": "17115001", "Name:": "ABHINAV BYAHUT", "Company:": "AQR Capital India Services LLP", "Course:": "B.Tech.", "Accepted:": "Yes "}, {"Enrollment no:": "17115003", "Name:": "ABHISHEK BHADAURIA", "Company:": "Axis Bank", "Course:": "B.Tech.", "Accepted:": "Yes "}, {"Enrollment no:": "17115004", "Name:": "ABHISHEK KARANATH", "Company:": "Cisco Systems", "Course:": "B.Tech.", "Accepted:": "Yes "}, {"Enrollment no:": "17115006", "Name:": "ABHISHEK SUNIL PAWAR", "Company:": "Futures First", "Course:": "B.Tech.", "Accepted:": "Yes "}, {"Enrollment no:": "17115011", "Name:": "AMAN BARYA", "Company:": "Innovaccer (SummerGeeks 2020)", "Course:": "B.Tech.", "Accepted:": "Yes "}, {"Enrollment no:": "17115012", "Name:": "ANJANEY RAI", "Company:": "Societe Generale", "Course:": "B.Tech.", "Accepted:": "Yes "}, {"Enrollment no:": "17115013", "Name:": "ANKIT", "Company:": "ZestMoney", "Course:": "B.Tech.", "Accepted:": "Yes "}, {"Enrollment no:": "17115014", "Name:": "ANKIT BHATI", "Company:": "SAMSUNG R&D INSTITUTE INDIA- DELHI(SRI-Delhi)", "Course:": "B.Tech.", "Accepted:": "Yes "}, {"Enrollment no:": "17115014", "Name:": "ANKIT BHATI", "Company:": "NoBroker[Software Development Intern]", "Course:": "B.Tech.", "Accepted:": "No"}, {"Enrollment no:": "17115019", "Name:": "ARYAN GOYAT", "Company:": "Microsoft (Software)", "Course:": "B.Tech.", "Accepted:": "Yes "}, {"Enrollment no:": "17115021", "Name:": "ASHISH ANAND", "Company:": "KPIT Technologies Ltd", "Course:": "B.Tech.", "Accepted:": "Yes "}, {"Enrollment no:": "17115024", "Name:": "AVNEET JAIN", "Company:": "Adobe Systems", "Course:": "B.Tech.", "Accepted:": "Yes "}, {"Enrollment no:": "17115024", "Name:": "AVNEET JAIN", "Company:": "Amazon", "Course:": "B.Tech.", "Accepted:": "No"}, {"Enrollment no:": "17115026", "Name:": "AYUSH KATIYAR", "Company:": "Microsoft (Software)", "Course:": "B.Tech.", "Accepted:": "Yes "}, {"Enrollment no:": "17115029", "Name:": "BIJENDER", "Company:": "SAMSUNG R&D INSTITUTE INDIA- DELHI(SRI-Delhi)", "Course:": "B.Tech.", "Accepted:": "Yes "}, {"Enrollment no:": "17115030", "Name:": "DEEPAK KUMAR", "Company:": "Wipro Star Summer Internship Programme 2020", "Course:": "B.Tech.", "Accepted:": "Yes "}, {"Enrollment no:": "17115031", "Name:": "DHIRAJ CHHAWCHHARIA", "Company:": "Axis Bank", "Course:": "B.Tech.", "Accepted:": "Yes "}, {"Enrollment no:": "17115033", "Name:": "EBTASAM UDDIN FARIDY", "Company:": "Myntra", "Course:": "B.Tech.", "Accepted:": "Yes "}, {"Enrollment no:": "17115034", "Name:": "ETTA DHEERAJ KUMAR REDDY", "Company:": "Adobe Systems (Direct Offer)", "Course:": "B.Tech.", "Accepted:": "No"}, {"Enrollment no:": "17115036", "Name:": "GOMATI PRASAD", "Company:": "Doubtnut", "Course:": "B.Tech.", "Accepted:": "Yes "}, {"Enrollment no:": "17115037", "Name:": "GOURAV KUMAR", "Company:": "Amazon", "Course:": "B.Tech.", "Accepted:": "Yes "}, {"Enrollment no:": "17115038", "Name:": "HARSHIT KHETAN", "Company:": "Flipkart", "Course:": "B.Tech.", "Accepted:": "Yes "}, {"Enrollment no:": "17115039", "Name:": "HARSHIT YADAV", "Company:": "Service now", "Course:": "B.Tech.", "Accepted:": "Yes "}, {"Enrollment no:": "17115040", "Name:": "HIMANI JAIN", "Company:": "Microsoft (Software)", "Course:": "B.Tech.", "Accepted:": "Yes "}, {"Enrollment no:": "17115041", "Name:": "HIMANSHU", "Company:": "Samsung R & D Institute Noida", "Course:": "B.Tech.", "Accepted:": "Yes "}, {"Enrollment no:": "17115042", "Name:": "ISHNEET DHIMAN", "Company:": "Medicento", "Course:": "B.Tech.", "Accepted:": "Yes "}, {"Enrollment no:": "17113048", "Name:": "JATIN VARSHNEY", "Company:": "Adobe Systems (Direct Offer)", "Course:": "B.Tech.", "Accepted:": "Yes "}, {"Enrollment no:": "17115046", "Name:": "JEETENDRA KUMAR", "Company:": "Auro Sundram Ply & Door (JV of centuryply)", "Course:": "B.Tech.", "Accepted:": "Yes "}, {"Enrollment no:": "17117041", "Name:": "KARTICA MODI", "Company:": "JP Morgan Chase & Co (Quant)", "Course:": "B.Tech.", "Accepted:": "No"}, {"Enrollment no:": "17117041", "Name:": "KARTICA MODI", "Company:": "Microsoft (Software)", "Course:": "B.Tech.", "Accepted:": "Yes "}, {"Enrollment no:": "17115049", "Name:": "MADHUR RAWAT", "Company:": "JP Morgan Chase & Co (Software)", "Course:": "B.Tech.", "Accepted:": "Yes "}, {"Enrollment no:": "17115050", "Name:": "MADUGULA LOHITHA", "Company:": "Google (Hardware)", "Course:": "B.Tech.", "Accepted:": "Yes "}, {"Enrollment no:": "17115051", "Name:": "MALVIKA AGARWAL", "Company:": "Citibank India", "Course:": "B.Tech.", "Accepted:": "Yes "}, {"Enrollment no:": "17115053", "Name:": "MANOJ PARIHAR", "Company:": "Amazon", "Course:": "B.Tech.", "Accepted:": "Yes "}, {"Enrollment no:": "17115054", "Name:": "MIHIR NARAYAN", "Company:": "ZestMoney", "Course:": "B.Tech.", "Accepted:": "Yes "}, {"Enrollment no:": "17115056", "Name:": "MOHIT KUMAR GUPTA", "Company:": "ITC Limited", "Course:": "B.Tech.", "Accepted:": "Yes "}, {"Enrollment no:": "17115057", "Name:": "MRITUNJAY GUPTA", "Company:": "Rupeek (SDE)", "Course:": "B.Tech.", "Accepted:": "Yes "}, {"Enrollment no:": "17115059", "Name:": "NISHANT", "Company:": "ZestMoney", "Course:": "B.Tech.", "Accepted:": "Yes "}, {"Enrollment no:": "17115062", "Name:": "PAREPALLI THARUN KUMAR", "Company:": "ZestMoney", "Course:": "B.Tech.", "Accepted:": "Yes "}, {"Enrollment no:": "17115064", "Name:": "POTNURU CHANUKYA", "Company:": "Texas Instruments", "Course:": "B.Tech.", "Accepted:": "Yes "}, {"Enrollment no:": "17113096", "Name:": "PURVI AGARWAL", "Company:": "Texas Instruments", "Course:": "B.Tech.", "Accepted:": "Yes "}, {"Enrollment no:": "17115069", "Name:": "RAHUL AVINASH BADWAIK", "Company:": "Philips India Limited", "Course:": "B.Tech.", "Accepted:": "Yes "}, {"Enrollment no:": "17115070", "Name:": "RAHUL KUMAR", "Company:": "Samsung R&D Bangalore", "Course:": "B.Tech.", "Accepted:": "Yes "}, {"Enrollment no:": "17115071", "Name:": "RAJ NARNOLI", "Company:": "Samsung Semiconductor (HW)", "Course:": "B.Tech.", "Accepted:": "Yes "}, {"Enrollment no:": "17115074", "Name:": "RISANA RASHEED K", "Company:": "Amazon", "Course:": "B.Tech.", "Accepted:": "Yes "}, {"Enrollment no:": "17115075", "Name:": "ROUNIK BALIDA", "Company:": "SAMSUNG R&D INSTITUTE INDIA- DELHI(SRI-Delhi)", "Course:": "B.Tech.", "Accepted:": "Yes "}, {"Enrollment no:": "17115076", "Name:": "SAMARTH AGARWAL", "Company:": "Goldman Sachs", "Course:": "B.Tech.", "Accepted:": "Yes "}, {"Enrollment no:": "17115078", "Name:": "SANYAM AGRAWAL", "Company:": "Samsung R&D Bangalore", "Course:": "B.Tech.", "Accepted:": "Yes "}, {"Enrollment no:": "17115079", "Name:": "SARTHAK GUPTA", "Company:": "Qualcomm (HW)", "Course:": "B.Tech.", "Accepted:": "Yes "}, {"Enrollment no:": "17115081", "Name:": "SATYANSH KUMAR RAI", "Company:": "NVIDIA", "Course:": "B.Tech.", "Accepted:": "Yes "}, {"Enrollment no:": "17115082", "Name:": "SAURAV JHANWAR", "Company:": "SAMSUNG R&D INSTITUTE INDIA- DELHI(SRI-Delhi)", "Course:": "B.Tech.", "Accepted:": "Yes "}, {"Enrollment no:": "17115086", "Name:": "SHIVAM CHOPRA", "Company:": "Oracle India Pvt. Ltd.", "Course:": "B.Tech.", "Accepted:": "Yes "}, {"Enrollment no:": "17115087", "Name:": "SHIVAM NIRMAL", "Company:": "Bajaj Auto Ltd", "Course:": "B.Tech.", "Accepted:": "Yes "}, {"Enrollment no:": "17115089", "Name:": "SHIVANSH KUMAR", "Company:": "AppDynamics India Pvt Ltd", "Course:": "B.Tech.", "Accepted:": "Yes "}, {"Enrollment no:": "17115090", "Name:": "SHIVANSHU GUPTA", "Company:": "GE Healthcare", "Course:": "B.Tech.", "Accepted:": "Yes "}, {"Enrollment no:": "17117079", "Name:": "SHREEYASH GEDA", "Company:": "Bidgley (Data Science)", "Course:": "B.Tech.", "Accepted:": "Yes "}, {"Enrollment no:": "17115091", "Name:": "SHREYANSH JAIN", "Company:": "Goldman Sachs", "Course:": "B.Tech.", "Accepted:": "Yes "}, {"Enrollment no:": "17115092", "Name:": "SHRUTI PRAFULLA NALE", "Company:": "Wipro Star Summer Internship Programme 2020", "Course:": "B.Tech.", "Accepted:": "Yes "}, {"Enrollment no:": "17115093", "Name:": "SHUBHAM BIHANI", "Company:": "Texas Instruments", "Course:": "B.Tech.", "Accepted:": "Yes "}, {"Enrollment no:": "17115097", "Name:": "SUDHIR ROSE", "Company:": "GE Healthcare", "Course:": "B.Tech.", "Accepted:": "Yes "}, {"Enrollment no:": "17115099", "Name:": "SUSHIL KUMAR", "Company:": "Service now", "Course:": "B.Tech.", "Accepted:": "Yes "}, {"Enrollment no:": "17115100", "Name:": "SUYASH JAIN", "Company:": "American Express (Technology)", "Course:": "B.Tech.", "Accepted:": "Yes "}, {"Enrollment no:": "17115103", "Name:": "TANISHK SAXENA", "Company:": "Bidgley (Software)", "Course:": "B.Tech.", "Accepted:": "Yes "}, {"Enrollment no:": "17115104", "Name:": "TANMAYA KHANDELWAL", "Company:": "D E Shaw India Pvt. Ltd.", "Course:": "B.Tech.", "Accepted:": "Yes "}, {"Enrollment no:": "17115105", "Name:": "TEJAS GAJANAN PATIL", "Company:": "Intuit", "Course:": "B.Tech.", "Accepted:": "Yes "}, {"Enrollment no:": "17115106", "Name:": "TRIBHUVAN SHARMA", "Company:": "Samsung R&D Bangalore", "Course:": "B.Tech.", "Accepted:": "Yes "}, {"Enrollment no:": "17115107", "Name:": "TUSHAR GOYAL", "Company:": "SAMSUNG R&D INSTITUTE INDIA- DELHI(SRI-Delhi)", "Course:": "B.Tech.", "Accepted:": "Yes "}, {"Enrollment no:": "17115109", "Name:": "VIBHOR VERMA", "Company:": "Oracle India Pvt. Ltd.", "Course:": "B.Tech.", "Accepted:": "Yes "}, {"Enrollment no:": "17115111", "Name:": "VIDIT AGRAWAL", "Company:": "American Express (Analytics)", "Course:": "B.Tech.", "Accepted:": "Yes "}, {"Enrollment no:": "17115118", "Name:": "VIVEK HARISH MAHESHWARI", "Company:": "American Express (Analytics)", "Course:": "B.Tech.", "Accepted:": "Yes "}, {"Enrollment no:": "17115120", "Name:": "YEMPATI BHAVANA", "Company:": "Citibank India", "Course:": "B.Tech.", "Accepted:": "Yes "}], "ECE": [{"Enrollment no:": "17116004", "Name:": "ABHISHEK AGRAWAL", "Company:": "BNY Mellon Technology", "Course:": "B.Tech.", "Accepted:": "Yes "}, {"Enrollment no:": "17115005", "Name:": "ABHISHEK PANDE", "Company:": "Adobe Systems (Direct Offer)", "Course:": "B.Tech.", "Accepted:": "Yes "}, {"Enrollment no:": "17116007", "Name:": "ADITYA RAJ", "Company:": "Amazon", "Course:": "B.Tech.", "Accepted:": "No"}, {"Enrollment no:": "17116007", "Name:": "ADITYA RAJ", "Company:": "OLA Cabs (Research Engineer)", "Course:": "B.Tech.", "Accepted:": "Yes "}, {"Enrollment no:": "17116008", "Name:": "ANIKET MATHUR", "Company:": "JP Morgan Chase & Co (Software)", "Course:": "B.Tech.", "Accepted:": "Yes "}, {"Enrollment no:": "17116009", "Name:": "ANKIT ANVESH", "Company:": "Flipkart", "Course:": "B.Tech.", "Accepted:": "Yes "}, {"Enrollment no:": "17116010", "Name:": "ANKIT DHINDHWAL", "Company:": "Visa Inc", "Course:": "B.Tech.", "Accepted:": "Yes "}, {"Enrollment no:": "17116011", "Name:": "ANMOL BANSAL", "Company:": "Goldman Sachs", "Course:": "B.Tech.", "Accepted:": "Yes "}, {"Enrollment no:": "17116012", "Name:": "ANMOL JAIN", "Company:": "ITC Limited", "Course:": "B.Tech.", "Accepted:": "Yes "}, {"Enrollment no:": "17116015", "Name:": "ARPIT GUPTA", "Company:": "American Express (Technology)", "Course:": "B.Tech.", "Accepted:": "Yes "}, {"Enrollment no:": "17116017", "Name:": "ASHWINI SHARMA", "Company:": "Cisco Systems", "Course:": "B.Tech.", "Accepted:": "Yes "}, {"Enrollment no:": "17116018", "Name:": "ATLURI HITESH", "Company:": "SAMSUNG R&D INSTITUTE INDIA- DELHI(SRI-Delhi)", "Course:": "B.Tech.", "Accepted:": "Yes "}, {"Enrollment no:": "17116019", "Name:": "AYUSH GUPTA", "Company:": "SAMSUNG R&D INSTITUTE INDIA- DELHI(SRI-Delhi)", "Course:": "B.Tech.", "Accepted:": "Yes "}, {"Enrollment no:": "17116020", "Name:": "AYUSH NAWAL", "Company:": "Amazon", "Course:": "B.Tech.", "Accepted:": "Yes "}, {"Enrollment no:": "17118017", "Name:": "B SAI AKSHAY", "Company:": "Samsung R & D Institute Noida", "Course:": "B.Tech.", "Accepted:": "Yes "}, {"Enrollment no:": "17116023", "Name:": "CHIRAYU GARG", "Company:": "PayU", "Course:": "B.Tech.", "Accepted:": "Yes "}, {"Enrollment no:": "17116024", "Name:": "DHRUV SEHGAL", "Company:": "TCS", "Course:": "B.Tech.", "Accepted:": "No"}, {"Enrollment no:": "17116024", "Name:": "DHRUV SEHGAL", "Company:": "PayU", "Course:": "B.Tech.", "Accepted:": "Yes "}, {"Enrollment no:": "17116025", "Name:": "GAURAV KUMAR", "Company:": "Signal Intelligence (DIA)", "Course:": "B.Tech.", "Accepted:": "Yes "}, {"Enrollment no:": "17116026", "Name:": "GAURAV PAL", "Company:": "Innovaccer (SummerGeeks 2020)", "Course:": "B.Tech.", "Accepted:": "Yes "}, {"Enrollment no:": "17116027", "Name:": "GAURAV SINGLA", "Company:": "Bidgley (Software)", "Course:": "B.Tech.", "Accepted:": "Yes "}, {"Enrollment no:": "17116029", "Name:": "ISHAN JINDAL", "Company:": "Adobe Systems (Direct Offer)", "Course:": "B.Tech.", "Accepted:": "Yes "}, {"Enrollment no:": "17116030", "Name:": "KANCHARLA RAVI TEJA", "Company:": "GE Digital", "Course:": "B.Tech.", "Accepted:": "Yes "}, {"Enrollment no:": "17116031", "Name:": "KAVURU SAHIT SAI SRIRAM", "Company:": "Qualcomm (HW)", "Course:": "B.Tech.", "Accepted:": "Yes "}, {"Enrollment no:": "17116032", "Name:": "KIRTHI MOULIKA", "Company:": "Adobe Systems", "Course:": "B.Tech.", "Accepted:": "Yes "}, {"Enrollment no:": "17116033", "Name:": "KISHORE K G", "Company:": "Cisco Systems", "Course:": "B.Tech.", "Accepted:": "Yes "}, {"Enrollment no:": "17116035", "Name:": "Kripa Shankar", "Company:": "TCS", "Course:": "B.Tech.", "Accepted:": "Yes "}, {"Enrollment no:": "17116036", "Name:": "MADAMSHETTI NAGASAI", "Company:": "Cisco Systems", "Course:": "B.Tech.", "Accepted:": "Yes "}, {"Enrollment no:": "17116037", "Name:": "MADDUKURI VIKAS", "Company:": "Adobe Systems", "Course:": "B.Tech.", "Accepted:": "Yes "}, {"Enrollment no:": "17116038", "Name:": "MARAM SUMANTH", "Company:": "Goldman Sachs", "Course:": "B.Tech.", "Accepted:": "Yes "}, {"Enrollment no:": "17116039", "Name:": "MAYANK MEHTA", "Company:": "Texas Instruments", "Course:": "B.Tech.", "Accepted:": "Yes "}, {"Enrollment no:": "17116041", "Name:": "MOHIT", "Company:": "Visa Inc", "Course:": "B.Tech.", "Accepted:": "Yes "}, {"Enrollment no:": "17116042", "Name:": "MUKUND KRISHNATREY", "Company:": "Cisco Systems", "Course:": "B.Tech.", "Accepted:": "Yes "}, {"Enrollment no:": "17116043", "Name:": "MUNAGAPATI VENKATA SAI ABHISHEK", "Company:": "SAMSUNG R&D INSTITUTE INDIA- DELHI(SRI-Delhi)", "Course:": "B.Tech.", "Accepted:": "Yes "}, {"Enrollment no:": "17116045", "Name:": "NAMAN SINGHAL", "Company:": "Amazon", "Course:": "B.Tech.", "Accepted:": "Yes "}, {"Enrollment no:": "17116051", "Name:": "PANIGRAHY VARUN RAJ", "Company:": "Goldman Sachs", "Course:": "B.Tech.", "Accepted:": "No"}, {"Enrollment no:": "17116051", "Name:": "PANIGRAHY VARUN RAJ", "Company:": "Microsoft (Software)", "Course:": "B.Tech.", "Accepted:": "Yes "}, {"Enrollment no:": "17116052", "Name:": "PANKAJ KUMAR SINGH", "Company:": "Doubtnut", "Course:": "B.Tech.", "Accepted:": "Yes "}, {"Enrollment no:": "17116053", "Name:": "PANKAJ SINGLA", "Company:": "Envestnet Yodlee", "Course:": "B.Tech.", "Accepted:": "Yes "}, {"Enrollment no:": "17116055", "Name:": "RAHUL PATIL", "Company:": "SAMSUNG R&D INSTITUTE INDIA- DELHI(SRI-Delhi)", "Course:": "B.Tech.", "Accepted:": "Yes "}, {"Enrollment no:": "17116058", "Name:": "RITICK GOENKA", "Company:": "Sprinklr India Pvt. Ltd.", "Course:": "B.Tech.", "Accepted:": "Yes "}, {"Enrollment no:": "17116059", "Name:": "RITIK JAIN", "Company:": "Amazon", "Course:": "B.Tech.", "Accepted:": "Yes "}, {"Enrollment no:": "17116060", "Name:": "RIYA BHALLA", "Company:": "Microsoft (PIO)", "Course:": "B.Tech.", "Accepted:": "Yes "}, {"Enrollment no:": "17116061", "Name:": "SAGAR PRATEEK", "Company:": "Service now", "Course:": "B.Tech.", "Accepted:": "Yes "}, {"Enrollment no:": "17116063", "Name:": "SANJAY YADAV", "Company:": "SAMSUNG R&D INSTITUTE INDIA- DELHI(SRI-Delhi)", "Course:": "B.Tech.", "Accepted:": "Yes "}, {"Enrollment no:": "17116064", "Name:": "SANKHADEEP GAIN", "Company:": "Biz-Metric India Pvt. Ltd.", "Course:": "B.Tech.", "Accepted:": "Yes "}, {"Enrollment no:": "17116065", "Name:": "SARTHAK SACHDEVA", "Company:": "Google (Software)", "Course:": "B.Tech.", "Accepted:": "Yes "}, {"Enrollment no:": "17116066", "Name:": "SHARON LAWANG", "Company:": "Optum", "Course:": "B.Tech.", "Accepted:": "Yes "}, {"Enrollment no:": "17116067", "Name:": "SHREY JAIN", "Company:": "SAMSUNG R&D INSTITUTE INDIA- DELHI(SRI-Delhi)", "Course:": "B.Tech.", "Accepted:": "Yes "}, {"Enrollment no:": "17116069", "Name:": "SPARSH JAIN", "Company:": "Amazon", "Course:": "B.Tech.", "Accepted:": "Yes "}, {"Enrollment no:": "17116071", "Name:": "SUPRATIK DAS", "Company:": "American Express (Technology)", "Course:": "B.Tech.", "Accepted:": "Yes "}, {"Enrollment no:": "17116072", "Name:": "SURAJ VASTRI", "Company:": "Auro Sundram Ply & Door (JV of centuryply)", "Course:": "B.Tech.", "Accepted:": "Yes "}, {"Enrollment no:": "17116074", "Name:": "TILAK RAJ CHORDIYA", "Company:": "Next Education India Pvt. Ltd.", "Course:": "B.Tech.", "Accepted:": "No"}, {"Enrollment no:": "17116075", "Name:": "TUSHAR BANSAL", "Company:": "Adobe Systems (Direct Offer)", "Course:": "B.Tech.", "Accepted:": "No"}, {"Enrollment no:": "17116076", "Name:": "VIVEK SINGH THAKUR", "Company:": "Samsung Semiconductor (HW)", "Course:": "B.Tech.", "Accepted:": "Yes "}, {"Enrollment no:": "17116077", "Name:": "VOUTOUKURI TANUSREE REDDY", "Company:": "Gemini Solutions Private Limited", "Course:": "B.Tech.", "Accepted:": "Yes "}], "EPH": [{"Enrollment no:": "17122004", "Name:": "AJINKYA AMBADAS GORE", "Company:": "Citibank India", "Course:": "B.Tech.", "Accepted:": "Yes "}, {"Enrollment no:": "17122010", "Name:": "GAGAN SINGH SAINI", "Company:": "NoBroker[Data Scientist]", "Course:": "B.Tech.", "Accepted:": "Yes "}, {"Enrollment no:": "17122016", "Name:": "NIDHI NAYAK", "Company:": "Doubtnut", "Course:": "B.Tech.", "Accepted:": "Yes "}, {"Enrollment no:": "17118057", "Name:": "RITESH CHHETRI", "Company:": "Biz-Metric India Pvt. Ltd.", "Course:": "B.Tech.", "Accepted:": "Yes "}], "GT": [{"Enrollment no:": "16410008", "Name:": "ANIRUDH DAGAR", "Company:": "Schlumberger software", "Course:": "IMT", "Accepted:": "Yes "}, {"Enrollment no:": "16410013", "Name:": "FARAZ JAMAL ZAIDI", "Company:": "Publicis Sapient [DS]", "Course:": "IMT", "Accepted:": "Yes "}, {"Enrollment no:": "16410017", "Name:": "MADHVENDRA PRATAP SINGH", "Company:": "Axxela Advisory Services", "Course:": "IMT", "Accepted:": "Yes "}, {"Enrollment no:": "16410025", "Name:": "SIDDHARTHA LOVEWANSHI", "Company:": "Rural Handmade|", "Course:": "IMT", "Accepted:": "Yes "}, {"Enrollment no:": "16410029", "Name:": "TEJAS WARATHE", "Company:": "Societe Generale", "Course:": "IMT", "Accepted:": "Yes "}], "GPT": [{"Enrollment no:": "16411004", "Name:": "ALEN", "Company:": "Eatler India", "Course:": "IMT", "Accepted:": "Yes "}, {"Enrollment no:": "16411010", "Name:": "KUNAL SHARMA", "Company:": "ExxonMobil", "Course:": "IMT", "Accepted:": "Yes "}, {"Enrollment no:": "16411012", "Name:": "LAVNISH GUPTA", "Company:": "Vedanta Oil & Gas", "Course:": "IMT", "Accepted:": "Yes "}, {"Enrollment no:": "16411014", "Name:": "MANISH SHARMA", "Company:": "ExxonMobil", "Course:": "IMT", "Accepted:": "Yes "}, {"Enrollment no:": "16411015", "Name:": "PRANAY LAWHATRE", "Company:": "Rural Handmade|", "Course:": "IMT", "Accepted:": "Yes "}, {"Enrollment no:": "16411017", "Name:": "RISHABH RAINA", "Company:": "Cognext Analytics Pvt. Ltd.", "Course:": "IMT", "Accepted:": "Yes "}, {"Enrollment no:": "16411018", "Name:": "SAHIL KUMAR", "Company:": "Futures First", "Course:": "IMT", "Accepted:": "Yes "}, {"Enrollment no:": "16411019", "Name:": "SALONI AGARWAL", "Company:": "TMI Network", "Course:": "IMT", "Accepted:": "Yes "}, {"Enrollment no:": "16410021", "Name:": "SAMBIT SARKAR", "Company:": "Eatler India", "Course:": "IMT", "Accepted:": "Yes "}, {"Enrollment no:": "16411031", "Name:": "VISHAL PUROHIT", "Company:": "ExxonMobil", "Course:": "IMT", "Accepted:": "Yes "}, {"Enrollment no:": "16411032", "Name:": "VISHVENDRA SINGH", "Company:": "ExxonMobil", "Course:": "IMT", "Accepted:": "Yes "}], "INM": [{"Enrollment no:": "19544002", "Name:": "AMIT RANJAN KUMAR", "Company:": "Jindal Stainless (Hisar) Limited", "Course:": "M.Tech.", "Accepted:": "Yes "}, {"Enrollment no:": "19544008", "Name:": "PRANJAL SINGH", "Company:": "Jindal Stainless (Hisar) Limited", "Course:": "M.Tech.", "Accepted:": "Yes "}], "MDE": [{"Enrollment no:": "19539001", "Name:": "ABHINAV KUMAR SHARMA", "Company:": "Eaton", "Course:": "M.Tech.", "Accepted:": "Yes "}, {"Enrollment no:": "19539012", "Name:": "VIVEK RAHI", "Company:": "Eaton", "Course:": "M.Tech.", "Accepted:": "Yes "}], "MBA": [{"Enrollment no:": "19810006", "Name:": "ASHWIN CHHARI", "Company:": "Auro Sundram Ply & Door (JV of centuryply)", "Course:": "MBA", "Accepted:": "Yes "}, {"Enrollment no:": "19810011", "Name:": "KARAN ARVIND CHITRODA", "Company:": "Auro Sundram Ply & Door (JV of centuryply)", "Course:": "MBA", "Accepted:": "Yes "}, {"Enrollment no:": "19810030", "Name:": "RITURAJ RITWEEK", "Company:": "Auro Sundram Ply & Door (JV of centuryply)", "Course:": "MBA", "Accepted:": "Yes "}, {"Enrollment no:": "19810038", "Name:": "SHASHANK SWARUP", "Company:": "Auro Sundram Ply & Door (JV of centuryply)", "Course:": "MBA", "Accepted:": "Yes "}], "ME": [{"Enrollment no:": "17117002", "Name:": "ABHISHEK KR MISHRA", "Company:": "Bajaj Auto Ltd", "Course:": "B.Tech.", "Accepted:": "Yes "}, {"Enrollment no:": "17117003", "Name:": "ADITYA VERMA", "Company:": "Futures First", "Course:": "B.Tech.", "Accepted:": "Yes "}, {"Enrollment no:": "17117011", "Name:": "ANUPRIY SHRIVASTAVA", "Company:": "Optum", "Course:": "B.Tech.", "Accepted:": "Yes "}, {"Enrollment no:": "17117012", "Name:": "ANURAAG", "Company:": "Reliance Industries Limited", "Course:": "B.Tech.", "Accepted:": "Yes "}, {"Enrollment no:": "17117013", "Name:": "APAR HARSH CHANDRA", "Company:": "Standard Chartered ", "Course:": "B.Tech.", "Accepted:": "Yes "}, {"Enrollment no:": "17117014", "Name:": "ARPAN", "Company:": "Futures First", "Course:": "B.Tech.", "Accepted:": "Yes "}, {"Enrollment no:": "17117015", "Name:": "ATHARVA DHANESH GHADGE", "Company:": "ITC Limited", "Course:": "B.Tech.", "Accepted:": "Yes "}, {"Enrollment no:": "17117016", "Name:": "AYUSH KUMAR", "Company:": "Next Education India Pvt. Ltd.", "Course:": "B.Tech.", "Accepted:": "No"}, {"Enrollment no:": "17117016", "Name:": "AYUSH KUMAR", "Company:": "Next Education India Pvt. Ltd.", "Course:": "B.Tech.", "Accepted:": "No"}, {"Enrollment no:": "17113025", "Name:": "BHANU SINGHAL", "Company:": "Droom (All Profiles)", "Course:": "B.Tech.", "Accepted:": "Yes "}, {"Enrollment no:": "17117022", "Name:": "DEEPAK HARIDAS", "Company:": "Futures First", "Course:": "B.Tech.", "Accepted:": "Yes "}, {"Enrollment no:": "17117027", "Name:": "GAURAV SINGHAL", "Company:": "OLA Cabs (SDE]", "Course:": "B.Tech.", "Accepted:": "Yes "}, {"Enrollment no:": "17117033", "Name:": "HARSHIL KUMAR PATEL", "Company:": "NoBroker[Software Development Intern]", "Course:": "B.Tech.", "Accepted:": "Yes "}, {"Enrollment no:": "17117033", "Name:": "HARSHIL KUMAR PATEL", "Company:": "Next Education India Pvt. Ltd.", "Course:": "B.Tech.", "Accepted:": "No"}, {"Enrollment no:": "17117034", "Name:": "HARSHIT RAWAL", "Company:": "Optum", "Course:": "B.Tech.", "Accepted:": "Yes "}, {"Enrollment no:": "17117036", "Name:": "JATIN SHARMA", "Company:": "Goldman Sachs", "Course:": "B.Tech.", "Accepted:": "Yes "}, {"Enrollment no:": "17117042", "Name:": "KESHVAM", "Company:": "JSW Group", "Course:": "B.Tech.", "Accepted:": "Yes "}, {"Enrollment no:": "17117046", "Name:": "M S V S SAI PRUDHVI", "Company:": "Reliance Industries Limited", "Course:": "B.Tech.", "Accepted:": "Yes "}, {"Enrollment no:": "17117047", "Name:": "MAITRIK ASHISH SHAH", "Company:": "Bajaj Auto Ltd", "Course:": "B.Tech.", "Accepted:": "Yes "}, {"Enrollment no:": "17117048", "Name:": "MRIDUL AGARWAL", "Company:": "Reliance Industries Limited", "Course:": "B.Tech.", "Accepted:": "Yes "}, {"Enrollment no:": "17117050", "Name:": "NIKHIL AGRAWAL", "Company:": "Fidelity Investments", "Course:": "B.Tech.", "Accepted:": "Yes "}, {"Enrollment no:": "17117056", "Name:": "PIYUSH JADIYA", "Company:": "Udaan.com [BD]", "Course:": "B.Tech.", "Accepted:": "Yes "}, {"Enrollment no:": "17117069", "Name:": "RAVINDRA BADIYASAR", "Company:": "Doubtnut", "Course:": "B.Tech.", "Accepted:": "Yes "}, {"Enrollment no:": "17117070", "Name:": "RITIK ANAND", "Company:": "Standard Chartered ", "Course:": "B.Tech.", "Accepted:": "Yes "}, {"Enrollment no:": "17117071", "Name:": "RITWIK JHA", "Company:": "The Software Practice", "Course:": "B.Tech.", "Accepted:": "Yes "}, {"Enrollment no:": "17117075", "Name:": "SANSKAR CHORDIYA", "Company:": "Bajaj Auto Ltd", "Course:": "B.Tech.", "Accepted:": "Yes "}, {"Enrollment no:": "17117078", "Name:": "SHIVENDRU MATHUR", "Company:": "ITC Limited", "Course:": "B.Tech.", "Accepted:": "Yes "}, {"Enrollment no:": "17117080", "Name:": "SUBHRAM SUBHRAJYOTI RANA", "Company:": "Doubtnut", "Course:": "B.Tech.", "Accepted:": "Yes "}, {"Enrollment no:": "17117081", "Name:": "SUDHANSHU GUPTA", "Company:": "Service now", "Course:": "B.Tech.", "Accepted:": "Yes "}, {"Enrollment no:": "17117084", "Name:": "SWAMY ROHIT BHARTIYA", "Company:": "Doubtnut", "Course:": "B.Tech.", "Accepted:": "Yes "}, {"Enrollment no:": "17117091", "Name:": "UJJWAL BARANWAL", "Company:": "Udaan.com [Operations]", "Course:": "B.Tech.", "Accepted:": "Yes "}, {"Enrollment no:": "17117094", "Name:": "VAGISH DILAWARI", "Company:": "Optum", "Course:": "B.Tech.", "Accepted:": "Yes "}, {"Enrollment no:": "17117096", "Name:": "VISHAL AGRAHARI", "Company:": "Axxela Advisory Services", "Course:": "B.Tech.", "Accepted:": "Yes "}, {"Enrollment no:": "17117097", "Name:": "VISHAL RAI", "Company:": "ITC Limited", "Course:": "B.Tech.", "Accepted:": "No"}, {"Enrollment no:": "17117097", "Name:": "VISHAL RAI", "Company:": "Hindustan Unilever Limited", "Course:": "B.Tech.", "Accepted:": "Yes "}, {"Enrollment no:": "17117101", "Name:": "ZAID BIN JUNAID", "Company:": "Citibank India", "Course:": "B.Tech.", "Accepted:": "Yes "}], "MT": [{"Enrollment no:": "17118001", "Name:": "ABHAY MUDGAL", "Company:": "Axis Bank", "Course:": "B.Tech.", "Accepted:": "Yes "}, {"Enrollment no:": "17118003", "Name:": "ABHINAV GUPTA", "Company:": "Next Education India Pvt. Ltd.", "Course:": "B.Tech.", "Accepted:": "Yes "}, {"Enrollment no:": "17118005", "Name:": "ADINATH SANJAY CHAUDHARI", "Company:": "Udaan.com [BD]", "Course:": "B.Tech.", "Accepted:": "Yes "}, {"Enrollment no:": "17118006", "Name:": "ADITYA YADAV", "Company:": "Truebil.com (Operations)", "Course:": "B.Tech.", "Accepted:": "Yes "}, {"Enrollment no:": "17118011", "Name:": "AMAN KUMAR", "Company:": "HSBC (India)", "Course:": "B.Tech.", "Accepted:": "Yes "}, {"Enrollment no:": "17118016", "Name:": "AYUSHMAN", "Company:": "Doubtnut", "Course:": "B.Tech.", "Accepted:": "Yes "}, {"Enrollment no:": "17118023", "Name:": "GAURAV VIVEK DHELIA", "Company:": "Societe Generale", "Course:": "B.Tech.", "Accepted:": "Yes "}, {"Enrollment no:": "17118024", "Name:": "HARDIK AGARWAL", "Company:": "Citibank India", "Course:": "B.Tech.", "Accepted:": "Yes "}, {"Enrollment no:": "17118025", "Name:": "HARDIK TANEJA", "Company:": "Reliance Industries Limited", "Course:": "B.Tech.", "Accepted:": "Yes "}, {"Enrollment no:": "17118031", "Name:": "JAYESH SANJAY PATIL", "Company:": "NoBroker [Business Consultant]", "Course:": "B.Tech.", "Accepted:": "No"}, {"Enrollment no:": "17118031", "Name:": "JAYESH SANJAY PATIL", "Company:": "NoBroker [Business Consultant]", "Course:": "B.Tech.", "Accepted:": "No"}, {"Enrollment no:": "17118031", "Name:": "JAYESH SANJAY PATIL", "Company:": "NoBroker [Business Consultant]", "Course:": "B.Tech.", "Accepted:": "Yes "}, {"Enrollment no:": "17118031", "Name:": "JAYESH SANJAY PATIL", "Company:": "NoBroker [Business Consultant]", "Course:": "B.Tech.", "Accepted:": "No"}, {"Enrollment no:": "17118038", "Name:": "MAHIMA BHAVESH THAKKAR", "Company:": "GE Digital", "Course:": "B.Tech.", "Accepted:": "Yes "}, {"Enrollment no:": "17310008", "Name:": "MANYA GUPTA", "Company:": "American Express (Analytics)", "Course:": "B.Tech.", "Accepted:": "Yes "}, {"Enrollment no:": "17118047", "Name:": "NITYA MRINAL MESHRAM", "Company:": "Citibank India", "Course:": "B.Tech.", "Accepted:": "Yes "}, {"Enrollment no:": "17118049", "Name:": "PRACHI AGARWAL", "Company:": "Microsoft (PIO)", "Course:": "B.Tech.", "Accepted:": "Yes "}, {"Enrollment no:": "17118063", "Name:": "SATISH KUMAR RAJ", "Company:": "JSW Group", "Course:": "B.Tech.", "Accepted:": "Yes "}, {"Enrollment no:": "17121024", "Name:": "SAURABH KUMAR", "Company:": "Signal Intelligence (DIA)", "Course:": "B.Tech.", "Accepted:": "Yes "}, {"Enrollment no:": "17118067", "Name:": "SHUBHI MISHRA", "Company:": "Citibank India", "Course:": "B.Tech.", "Accepted:": "Yes "}], "MEV": [{"Enrollment no:": "19534001", "Name:": "ADABALA VENUGOPAL", "Company:": "Intel (Digital)", "Course:": "M.Tech.", "Accepted:": "Yes "}, {"Enrollment no:": "19534001", "Name:": "ADABALA VENUGOPAL", "Company:": "Samsung Semiconductor (HW)", "Course:": "M.Tech.", "Accepted:": "No"}, {"Enrollment no:": "19534005", "Name:": "BETHA SURYA PRAKASH", "Company:": "Qualcomm (HW)", "Course:": "M.Tech.", "Accepted:": "No"}, {"Enrollment no:": "19534005", "Name:": "BETHA SURYA PRAKASH", "Company:": "Intel (Digital)", "Course:": "M.Tech.", "Accepted:": "Yes "}, {"Enrollment no:": "19534006", "Name:": "HARSH MATHE", "Company:": "Qualcomm (HW)", "Course:": "M.Tech.", "Accepted:": "No"}, {"Enrollment no:": "19534006", "Name:": "HARSH MATHE", "Company:": "Intel (Digital)", "Course:": "M.Tech.", "Accepted:": "Yes "}, {"Enrollment no:": "19534009", "Name:": "KULKARNI SHWETA GAJANAN", "Company:": "Qualcomm (HW)", "Course:": "M.Tech.", "Accepted:": "No"}, {"Enrollment no:": "19534009", "Name:": "KULKARNI SHWETA GAJANAN", "Company:": "Intel (Digital)", "Course:": "M.Tech.", "Accepted:": "Yes "}, {"Enrollment no:": "19534012", "Name:": "RAKESH B", "Company:": "Intel (Digital)", "Course:": "M.Tech.", "Accepted:": "Yes "}, {"Enrollment no:": "19534013", "Name:": "SIVAPRASAD SANTHOSH LIKITH NARAYAN", "Company:": "Intel (Digital)", "Course:": "M.Tech.", "Accepted:": "Yes "}, {"Enrollment no:": "19534013", "Name:": "SIVAPRASAD SANTHOSH LIKITH NARAYAN", "Company:": "Qualcomm (HW)", "Course:": "M.Tech.", "Accepted:": "No"}], "PS": [{"Enrollment no:": "17121003", "Name:": "AKASH PANDIT GAJARE", "Company:": "Axis Bank", "Course:": "B.Tech.", "Accepted:": "Yes "}, {"Enrollment no:": "17121004", "Name:": "ALIASGAR NALAWALA", "Company:": "NoBroker [Business Consultant]", "Course:": "B.Tech.", "Accepted:": "Yes "}, {"Enrollment no:": "17121008", "Name:": "DINESH CHOUDHARY", "Company:": "Doubtnut", "Course:": "B.Tech.", "Accepted:": "Yes "}, {"Enrollment no:": "17121021", "Name:": "RAHUL SINGHAI", "Company:": "HyperVerge", "Course:": "B.Tech.", "Accepted:": "Yes "}, {"Enrollment no:": "17121031", "Name:": "VASU BANSAL", "Company:": "Futures First", "Course:": "B.Tech.", "Accepted:": "Yes "}], "PISE": [{"Enrollment no:": "19540009", "Name:": "SHUBHAM SHANKAR MOHOL", "Company:": "Jindal Stainless (Hisar) Limited", "Course:": "M.Tech.", "Accepted:": "Yes "}, {"Enrollment no:": "19540010", "Name:": "SUDEEP ROY", "Company:": "Jindal Stainless (Hisar) Limited", "Course:": "M.Tech.", "Accepted:": "Yes "}], "IN": [{"Enrollment no:": "17119012", "Name:": "DEVENDRA ICHHARAM MAHAJAN", "Company:": "KPIT Technologies Ltd", "Course:": "B.Tech.", "Accepted:": "Yes "}, {"Enrollment no:": "17119014", "Name:": "HARSH SAINI", "Company:": "Udaan.com [Operations]", "Course:": "B.Tech.", "Accepted:": "Yes "}, {"Enrollment no:": "17119015", "Name:": "HITENDRA SINGH", "Company:": "Optum", "Course:": "B.Tech.", "Accepted:": "Yes "}, {"Enrollment no:": "17118032", "Name:": "JEYASHREE V", "Company:": "HSBC (India)", "Course:": "B.Tech.", "Accepted:": "Yes "}, {"Enrollment no:": "17119026", "Name:": "SAUMYA DINESH GUPTA", "Company:": "Goldman Sachs", "Course:": "B.Tech.", "Accepted:": "Yes "}, {"Enrollment no:": "17119032", "Name:": "SURAJ R SIDDAYYANAVAR", "Company:": "Udaan.com [Operations]", "Course:": "B.Tech.", "Accepted:": "Yes "}, {"Enrollment no:": "17119035", "Name:": "TUSHAR VARSHNEY", "Company:": "Cogoport", "Course:": "B.Tech.", "Accepted:": "Yes "}, {"Enrollment no:": "17119038", "Name:": "VIVEK CHAND", "Company:": "Fidelity Investments", "Course:": "B.Tech.", "Accepted:": "Yes "}], "SAC": [{"Enrollment no:": "19530011", "Name:": "RACHAKONDA SAI KIRAN", "Company:": "Eaton", "Course:": "M.Tech.", "Accepted:": "Yes "}, {"Enrollment no:": "19530017", "Name:": "VIVEK SHARMA", "Company:": "Eaton", "Course:": "M.Tech.", "Accepted:": "Yes "}]}